[
  {
    "ContainingType": "IngatlanokBackend.Controllers.FelhasznaloController",
    "Method": "UpdateUser",
    "RelativePath": "api/Felhasznalo/{loginNev}",
    "HttpMethod": "PUT",
    "IsController": true,
    "Order": 0,
    "Parameters": [
      {
        "Name": "loginNev",
        "Type": "System.String",
        "IsRequired": true
      },
      {
        "Name": "updatedUserData",
        "Type": "IngatlanokBackend.DTOs.UpdateUserDTO",
        "IsRequired": true
      }
    ],
    "ReturnTypes": []
  },
  {
    "ContainingType": "IngatlanokBackend.Controllers.FelhasznaloController",
    "Method": "DeleteUser",
    "RelativePath": "api/Felhasznalo/delete/{loginName}",
    "HttpMethod": "DELETE",
    "IsController": true,
    "Order": 0,
    "Parameters": [
      {
        "Name": "loginName",
        "Type": "System.String",
        "IsRequired": true
      }
    ],
    "ReturnTypes": []
  },
  {
    "ContainingType": "IngatlanokBackend.Controllers.FelhasznaloController",
    "Method": "Login",
    "RelativePath": "api/Felhasznalo/login",
    "HttpMethod": "POST",
    "IsController": true,
    "Order": 0,
    "Parameters": [
      {
        "Name": "loginDTO",
        "Type": "IngatlanokBackend.DTOs.LoginDTO",
        "IsRequired": true
      }
    ],
    "ReturnTypes": []
  },
  {
    "ContainingType": "IngatlanokBackend.Controllers.FelhasznaloController",
    "Method": "Logout",
    "RelativePath": "api/Felhasznalo/logout",
    "HttpMethod": "POST",
    "IsController": true,
    "Order": 0,
    "Parameters": [
      {
        "Name": "logoutDTO",
        "Type": "IngatlanokBackend.DTOs.LogoutDTO",
        "IsRequired": true
      }
    ],
    "ReturnTypes": []
  },
  {
    "ContainingType": "IngatlanokBackend.Controllers.FelhasznaloController",
    "Method": "GetCurrentUser",
    "RelativePath": "api/Felhasznalo/me/{loginNev}",
    "HttpMethod": "GET",
    "IsController": true,
    "Order": 0,
    "Parameters": [
      {
        "Name": "loginNev",
        "Type": "System.String",
        "IsRequired": true
      }
    ],
    "ReturnTypes": []
  },
  {
    "ContainingType": "IngatlanokBackend.Controllers.FelhasznaloController",
    "Method": "Register1",
    "RelativePath": "api/Felhasznalo/Register",
    "HttpMethod": "POST",
    "IsController": true,
    "Order": 0,
    "Parameters": [
      {
        "Name": "registrationDTO",
        "Type": "IngatlanokBackend.DTOs.RegistrationDTO",
        "IsRequired": true
      }
    ],
    "ReturnTypes": []
  },
  {
    "ContainingType": "IngatlanokBackend.Controllers.FelhasznaloController",
    "Method": "RequestPasswordReset",
    "RelativePath": "api/Felhasznalo/RequestPasswordReset",
    "HttpMethod": "POST",
    "IsController": true,
    "Order": 0,
    "Parameters": [
      {
        "Name": "request",
        "Type": "IngatlanokBackend.DTOs.RequestPasswordResetDTO",
        "IsRequired": true
      }
    ],
    "ReturnTypes": []
  },
  {
    "ContainingType": "IngatlanokBackend.Controllers.FelhasznaloController",
    "Method": "ResetPassword",
    "RelativePath": "api/Felhasznalo/ResetPassword",
    "HttpMethod": "POST",
    "IsController": true,
    "Order": 0,
    "Parameters": [
      {
        "Name": "resetPasswordDTO",
        "Type": "IngatlanokBackend.DTOs.ResetPasswordDTO",
        "IsRequired": true
      }
    ],
    "ReturnTypes": []
  },
  {
    "ContainingType": "IngatlanokBackend.Controllers.IngatlanController",
    "Method": "Get",
    "RelativePath": "api/Ingatlan/ingatlanok",
    "HttpMethod": "GET",
    "IsController": true,
    "Order": 0,
    "Parameters": [],
    "ReturnTypes": []
  },
  {
    "ContainingType": "IngatlanokBackend.Controllers.IngatlanController",
    "Method": "Post",
    "RelativePath": "api/Ingatlan/ingatlanok",
    "HttpMethod": "POST",
    "IsController": true,
    "Order": 0,
    "Parameters": [
      {
        "Name": "ingatlan",
        "Type": "IngatlanokBackend.Models.Ingatlanok",
        "IsRequired": true
      }
    ],
    "ReturnTypes": []
  },
  {
    "ContainingType": "IngatlanokBackend.Controllers.IngatlanController",
    "Method": "Put",
    "RelativePath": "api/Ingatlan/ingatlanok/{id}",
    "HttpMethod": "PUT",
    "IsController": true,
    "Order": 0,
    "Parameters": [
      {
        "Name": "id",
        "Type": "System.Int32",
        "IsRequired": true
      },
      {
        "Name": "ingatlan",
        "Type": "IngatlanokBackend.Models.Ingatlanok",
        "IsRequired": true
      }
    ],
    "ReturnTypes": []
  },
  {
    "ContainingType": "IngatlanokBackend.Controllers.IngatlanController",
    "Method": "Delete",
    "RelativePath": "api/Ingatlan/ingatlanok/{id}",
    "HttpMethod": "DELETE",
    "IsController": true,
    "Order": 0,
    "Parameters": [
      {
        "Name": "id",
        "Type": "System.Int32",
        "IsRequired": true
      }
    ],
    "ReturnTypes": []
  },
  {
    "ContainingType": "IngatlanokBackend.Controllers.IngatlanController",
    "Method": "Get",
    "RelativePath": "api/Ingatlan/ingatlanok/{ingatlanId}",
    "HttpMethod": "GET",
    "IsController": true,
    "Order": 0,
    "Parameters": [
      {
        "Name": "ingatlanId",
        "Type": "System.Int32",
        "IsRequired": true
      }
    ],
    "ReturnTypes": []
  }
]